Workbook

Sheet Painel
A1: 📈 PAINEL DE PERFORMANCE
A2: Atualiza automaticamente conforme você preenche a aba Lançamentos.
A4: Indicador | B4: Valor | C4: Meta | D4: Status
A5: Investimento total | B5: =SUM(Lançamentos!E4:E55)
A6: Leads | B6: =SUM(Lançamentos!H4:H55)
A7: Conversas qualificadas | B7: =SUM(Lançamentos!I4:I55)
A8: Visitas agendadas | B8: =SUM(Lançamentos!J4:J55)
A9: Propostas | B9: =SUM(Lançamentos!K4:K55)
A10: Vendas | B10: =SUM(Lançamentos!L4:L55)
A11: CPL médio | B11: =IFERROR(SUM(Lançamentos!E4:E55)/SUM(Lançamentos!H4:H55),0) | C11: =Metas!$B$5 | D11: =IF(B11=0,"—",IF(B11<=C11,"✅ no alvo",IF(B11<=C11*1.5,"⚠️ atenção","🔴 caro")))
A12: Custo por conversa | B12: =IFERROR(SUM(Lançamentos!E4:E55)/SUM(Lançamentos!I4:I55),0) | C12: =Metas!$B$6 | D12: =IF(B12=0,"—",IF(B12<=C12,"✅ no alvo",IF(B12<=C12*1.5,"⚠️ atenção","🔴 caro")))
A13: Custo por visita | B13: =IFERROR(SUM(Lançamentos!E4:E55)/SUM(Lançamentos!J4:J55),0) | C13: =Metas!$B$7 | D13: =IF(B13=0,"—",IF(B13<=C13,"✅ no alvo",IF(B13<=C13*1.5,"⚠️ atenção","🔴 caro")))
A14: Custo por venda (CAC) | B14: =IFERROR(SUM(Lançamentos!E4:E55)/SUM(Lançamentos!L4:L55),0)
A15: Taxa Lead → Visita | B15: =IFERROR(SUM(Lançamentos!J4:J55)/SUM(Lançamentos!H4:H55),0) | C15: =Metas!$B$8 | D15: =IF(B15=0,"—",IF(B15>=C15,"✅ no alvo",IF(B15>=C15*0.7,"⚠️ atenção","🔴 baixo")))
A16: Taxa Visita → Proposta | B16: =IFERROR(SUM(Lançamentos!K4:K55)/SUM(Lançamentos!J4:J55),0) | C16: =Metas!$B$9 | D16: =IF(B16=0,"—",IF(B16>=C16,"✅ no alvo",IF(B16>=C16*0.7,"⚠️ atenção","🔴 baixo")))
A17: Taxa Proposta → Venda | B17: =IFERROR(SUM(Lançamentos!L4:L55)/SUM(Lançamentos!K4:K55),0) | C17: =Metas!$B$10 | D17: =IF(B17=0,"—",IF(B17>=C17,"✅ no alvo",IF(B17>=C17*0.7,"⚠️ atenção","🔴 baixo")))
A18: Receita (comissão) | B18: =SUM(Lançamentos!L4:L55)*Metas!$B$11
A19: ROAS (retorno/investido) | B19: =IFERROR((SUM(Lançamentos!L4:L55)*Metas!$B$11)/SUM(Lançamentos!E4:E55),0) | C19: =Metas!$B$12 | D19: =IF(B19=0,"—",IF(B19>=C19,"✅ no alvo",IF(B19>=C19*0.7,"⚠️ atenção","🔴 baixo")))

Sheet Metas
A1: 🎯 METAS / KPIs DE REFERÊNCIA
A2: Edite os alvos conforme sua praça e ticket. O Painel usa estes valores no semáforo.
A4: Indicador | B4: Alvo | C4: Formato
A5: CPL alvo (custo por lead) | B5: 12 | C5: R$
A6: Custo por conversa qualificada | B6: 60 | C6: R$
A7: Custo por visita agendada | B7: 300 | C7: R$
A8: Taxa Lead → Visita | B8: 0.2 | C8: %
A9: Taxa Visita → Proposta | B9: 0.4 | C9: %
A10: Taxa Proposta → Venda | B10: 0.45 | C10: %
A11: Comissão média por venda | B11: 12000 | C11: R$
A12: ROAS alvo (retorno s/ investimento) | B12: 5 | C12: x

Sheet Lançamentos
A1: 📊 LANÇAMENTOS DE CAMPANHA (registre dia a dia)
A3: Data | B3: Plataforma | C3: Campanha | D3: Etapa | E3: Investido | F3: Impressões | G3: Cliques | H3: Leads | I3: Conversas qualif. | J3: Visitas agend. | K3: Propostas | L3: Vendas | M3: CTR | N3: CPL | O3: Custo/Conversa
A4: 2026-06-01 | B4: Meta | C4: AQV|Meta|Msg|TOFU|Maceió | D4: TOFU | E4: 60 | F4: 18000 | G4: 420 | H4: 38 | I4: 9 | J4: 3 | K4: 1 | L4: 0 | M4: =IFERROR(G4/F4,0) | N4: =IFERROR(E4/H4,0) | O4: =IFERROR(E4/I4,0)
A5: 2026-06-01 | B5: Meta | C5: AQV|Meta|Leads|TOFU|MCMV | D5: TOFU | E5: 40 | F5: 15000 | G5: 300 | H5: 52 | I5: 7 | J5: 2 | K5: 1 | L5: 0 | M5: =IFERROR(G5/F5,0) | N5: =IFERROR(E5/H5,0) | O5: =IFERROR(E5/I5,0)
A6: 2026-06-01 | B6: Google | C6: AQV|Google|Search|BOFU | D6: BOFU | E6: 50 | F6: 2200 | G6: 140 | H6: 12 | I6: 6 | J6: 3 | K6: 2 | L6: 1 | M6: =IFERROR(G6/F6,0) | N6: =IFERROR(E6/H6,0) | O6: =IFERROR(E6/I6,0)
A7: 2026-06-02 | B7: Meta | C7: AQV|Meta|Msg|TOFU|Maceió | D7: TOFU | E7: 60 | F7: 19500 | G7: 455 | H7: 41 | I7: 11 | J7: 4 | K7: 1 | L7: 1 | M7: =IFERROR(G7/F7,0) | N7: =IFERROR(E7/H7,0) | O7: =IFERROR(E7/I7,0)
A8: 2026-06-02 | B8: Meta | C8: AQV|Meta|Msg|RMKT|Prova | D8: Retargeting | E8: 25 | F8: 8000 | G8: 260 | H8: 18 | I8: 9 | J8: 4 | K8: 2 | L8: 1 | M8: =IFERROR(G8/F8,0) | N8: =IFERROR(E8/H8,0) | O8: =IFERROR(E8/I8,0)
A9: 2026-06-02 | B9: Google | C9: AQV|Google|Search|BOFU | D9: BOFU | E9: 50 | F9: 2400 | G9: 150 | H9: 14 | I9: 7 | J9: 4 | K9: 2 | L9: 1 | M9: =IFERROR(G9/F9,0) | N9: =IFERROR(E9/H9,0) | O9: =IFERROR(E9/I9,0)
A10: 2026-06-03 | B10: Meta | C10: AQV|Meta|Msg|TOFU|Investidor | D10: TOFU | E10: 40 | F10: 12000 | G10: 300 | H10: 22 | I10: 8 | J10: 2 | K10: 1 | L10: 0 | M10: =IFERROR(G10/F10,0) | N10: =IFERROR(E10/H10,0) | O10: =IFERROR(E10/I10,0)
A11: 2026-06-03 | B11: TikTok | C11: AQV|TikTok|Leads|TOFU|MCMV | D11: TOFU | E11: 40 | F11: 40000 | G11: 900 | H11: 80 | I11: 6 | J11: 1 | K11: 0 | L11: 0 | M11: =IFERROR(G11/F11,0) | N11: =IFERROR(E11/H11,0) | O11: =IFERROR(E11/I11,0)
A12: 2026-06-03 | B12: Meta | C12: AQV|Meta|Msg|BOFU|Fechamento | D12: BOFU | E12: 20 | F12: 3000 | G12: 120 | H12: 10 | I12: 7 | J12: 5 | K12: 3 | L12: 2 | M12: =IFERROR(G12/F12,0) | N12: =IFERROR(E12/H12,0) | O12: =IFERROR(E12/I12,0)
A13: 2026-06-04 | B13: Meta | C13: AQV|Meta|Msg|TOFU|Maceió | D13: TOFU | E13: 70 | F13: 21000 | G13: 500 | H13: 45 | I13: 12 | J13: 5 | K13: 2 | L13: 1 | M13: =IFERROR(G13/F13,0) | N13: =IFERROR(E13/H13,0) | O13: =IFERROR(E13/I13,0)
A14: 2026-06-04 | B14: Google | C14: AQV|Google|PMax|Escala | D14: Escala | E14: 50 | F14: 9000 | G14: 210 | H14: 20 | I14: 8 | J14: 3 | K14: 1 | L14: 1 | M14: =IFERROR(G14/F14,0) | N14: =IFERROR(E14/H14,0) | O14: =IFERROR(E14/I14,0)
A15: 2026-06-04 | B15: YouTube | C15: AQV|Google|DemandGen|RMKT | D15: Retargeting | E15: 30 | F15: 30000 | G15: 180 | H15: 9 | I15: 4 | J15: 2 | K15: 1 | L15: 0 | M15: =IFERROR(G15/F15,0) | N15: =IFERROR(E15/H15,0) | O15: =IFERROR(E15/I15,0)
M16: =IFERROR(G16/F16,0) | N16: =IFERROR(E16/H16,0) | O16: =IFERROR(E16/I16,0)
M17: =IFERROR(G17/F17,0) | N17: =IFERROR(E17/H17,0) | O17: =IFERROR(E17/I17,0)
M18: =IFERROR(G18/F18,0) | N18: =IFERROR(E18/H18,0) | O18: =IFERROR(E18/I18,0)
M19: =IFERROR(G19/F19,0) | N19: =IFERROR(E19/H19,0) | O19: =IFERROR(E19/I19,0)
M20: =IFERROR(G20/F20,0) | N20: =IFERROR(E20/H20,0) | O20: =IFERROR(E20/I20,0)
M21: =IFERROR(G21/F21,0) | N21: =IFERROR(E21/H21,0) | O21: =IFERROR(E21/I21,0)
M22: =IFERROR(G22/F22,0) | N22: =IFERROR(E22/H22,0) | O22: =IFERROR(E22/I22,0)
M23: =IFERROR(G23/F23,0) | N23: =IFERROR(E23/H23,0) | O23: =IFERROR(E23/I23,0)
M24: =IFERROR(G24/F24,0) | N24: =IFERROR(E24/H24,0) | O24: =IFERROR(E24/I24,0)
M25: =IFERROR(G25/F25,0) | N25: =IFERROR(E25/H25,0) | O25: =IFERROR(E25/I25,0)
M26: =IFERROR(G26/F26,0) | N26: =IFERROR(E26/H26,0) | O26: =IFERROR(E26/I26,0)
M27: =IFERROR(G27/F27,0) | N27: =IFERROR(E27/H27,0) | O27: =IFERROR(E27/I27,0)
... M55: =IFERROR(G55/F55,0) | N55: =IFERROR(E55/H55,0) | O55: =IFERROR(E55/I55,0)

Sheet Funil de Vendas
A1: 🧭 FUNIL DE VENDAS (atendimentos atuais)
H2: Resumo do funil →
A3: Lead | B3: Origem | C3: Entrada | D3: Estágio | E3: Imóvel | F3: Valor imóvel | G3: Comissão potencial | H3: Última interação | I3: Dias parado | J3: Próxima ação | L3: Estágio | M3: Qtd
A4: Marina S. | B4: Meta | C4: 2026-06-01 | D4: Visita agendada | E4: Apê 2q [Bairro] | F4: 389000 | G4: =F4*0.05 | H4: 2026-06-04 | I4: =TODAY()-H4 | J4: Confirmar visita sáb | L4: Conversa iniciada | M4: =COUNTIF($D$4:$D$38,"Conversa iniciada")
A5: João P. | B5: Google | C5: 2026-06-02 | D5: Proposta | E5: Cobertura frente-mar | F5: 1200000 | G5: =F5*0.05 | H5: 2026-06-05 | I5: =TODAY()-H5 | J5: Negociar contraproposta | L5: Qualificado | M5: =COUNTIF($D$4:$D$38,"Qualificado")
A6: Ana e Léo | B6: Meta | C6: 2026-06-02 | D6: Qualificado | E6: Apê 3q upgrade | F6: 560000 | G6: =F6*0.05 | H6: 2026-06-03 | I6: =TODAY()-H6 | J6: Enviar simulação | L6: Visita agendada | M6: =COUNTIF($D$4:$D$38,"Visita agendada")
A7: Carlos M. | B7: TikTok | C7: 2026-06-03 | D7: Conversa iniciada | E7: MCMV 2q | F7: 250000 | G7: =F7*0.05 | H7: 2026-06-03 | I7: =TODAY()-H7 | J7: Qualificar renda/FGTS | L7: Proposta | M7: =COUNTIF($D$4:$D$38,"Proposta")
A8: Investidor RJ | B8: Meta | C8: 2026-06-03 | D8: Qualificado | E8: Studio frente-mar | F8: 430000 | G8: =F8*0.05 | H8: 2026-06-04 | I8: =TODAY()-H8 | J8: Enviar estudo ROI | L8: Venda | M8: =COUNTIF($D$4:$D$38,"Venda")
G9: =IFERROR(F9*0.05,0) | I9: =IF(H9="","",TODAY()-H9) | L9: Perdido | M9: =COUNTIF($D$4:$D$38,"Perdido")
G10: =IFERROR(F10*0.05,0) | I10: =IF(H10="","",TODAY()-H10)
G11: =IFERROR(F11*0.05,0) | I11: =IF(H11="","",TODAY()-H11)
G12: =IFERROR(F12*0.05,0) | I12: =IF(H12="","",TODAY()-H12)
G13: =IFERROR(F13*0.05,0) | I13: =IF(H13="","",TODAY()-H13)
G14: =IFERROR(F14*0.05,0) | I14: =IF(H14="","",TODAY()-H14)
G15: =IFERROR(F15*0.05,0) | I15: =IF(H15="","",TODAY()-H15)
G16: =IFERROR(F16*0.05,0) | I16: =IF(H16="","",TODAY()-H16)
G17: =IFERROR(F17*0.05,0) | I17: =IF(H17="","",TODAY()-H17)
G18: =IFERROR(F18*0.05,0) | I18: =IF(H18="","",TODAY()-H18)
G19: =IFERROR(F19*0.05,0) | I19: =IF(H19="","",TODAY()-H19)
G20: =IFERROR(F20*0.05,0) | I20: =IF(H20="","",TODAY()-H20)
G21: =IFERROR(F21*0.05,0) | I21: =IF(H21="","",TODAY()-H21)
... G38: =IFERROR(F38*0.05,0) | I38: =IF(H38="","",TODAY()-H38)
